{
	"configurations" : 
	[
		{
			"directories" : 
			[
				{
					"build" : ".",
					"minimumCMakeVersion" : 
					{
						"string" : "3.0"
					},
					"projectIndex" : 0,
					"source" : ".",
					"targetIndexes" : 
					[
						0,
						1,
						2,
						3,
						4
					]
				}
			],
			"name" : "Debug",
			"projects" : 
			[
				{
					"directoryIndexes" : 
					[
						0
					],
					"name" : "zdunk",
					"targetIndexes" : 
					[
						0,
						1,
						2,
						3,
						4
					]
				}
			],
			"targets" : 
			[
				{
					"directoryIndex" : 0,
					"id" : "test::@6890427a1f51a3e7e1df",
					"jsonFile" : "target-test-Debug-064ceab554513a5a9138.json",
					"name" : "test",
					"projectIndex" : 0
				},
				{
					"directoryIndex" : 0,
					"id" : "test_config::@6890427a1f51a3e7e1df",
					"jsonFile" : "target-test_config-Debug-0ee14d4bafdd3dad02e3.json",
					"name" : "test_config",
					"projectIndex" : 0
				},
				{
					"directoryIndex" : 0,
					"id" : "test_thread::@6890427a1f51a3e7e1df",
					"jsonFile" : "target-test_thread-Debug-a26e3038746e7608aaa5.json",
					"name" : "test_thread",
					"projectIndex" : 0
				},
				{
					"directoryIndex" : 0,
					"id" : "test_utils::@6890427a1f51a3e7e1df",
					"jsonFile" : "target-test_utils-Debug-e17a61939bbd58c8a657.json",
					"name" : "test_utils",
					"projectIndex" : 0
				},
				{
					"directoryIndex" : 0,
					"id" : "zdunk::@6890427a1f51a3e7e1df",
					"jsonFile" : "target-zdunk-Debug-1857d95d8f83144dfe7b.json",
					"name" : "zdunk",
					"projectIndex" : 0
				}
			]
		}
	],
	"kind" : "codemodel",
	"paths" : 
	{
		"build" : "/home/zdunk/workspace/zdunking/build",
		"source" : "/home/zdunk/workspace/zdunking"
	},
	"version" : 
	{
		"major" : 2,
		"minor" : 0
	}
}
